[
  {
    "question": "Как Вам следует поступить в данной ситуации?",
    "image": "question_001.jpg",
    "answers": [
      "Проехать первым.",
      "Использовать обочину для встречного разъезда.",
      "Уступить дорогу грузовому автомобилю."
    ],
    "correct_answer": "Проехать первым."
  },
  {
    "question": "Как Вам следует поступить в данной ситуации?",
    "image": "question_002.jpg",
    "answers": [
      "Проехать первым.",
      "Уступить дорогу встречному автомобилю.",
      "Действовать по взаимной договоренности с водителем встречного автомобиля."
    ],
    "correct_answer": "Уступить дорогу встречному автомобилю."
  },
  {
    "question": "В данной ситуации Вы:",
    "image": "question_003.jpg",
    "answers": [
      "Должны уступить дорогу, так как встречный автомобиль движется на спуск.",
      "Должны уступить дорогу, так как препятствие находится на Вашей полосе движения.",
      "Имеете право проехать первым, так как Вы движетесь на подъем."
    ],
    "correct_answer": "Имеете право проехать первым, так как Вы движетесь на подъем."
  },
  {
    "question": "При наличии какого знака водитель должен уступить дорогу, если встречный разъезд затруднен?",
    "image": "question_004.jpg",
    "answers": [
      "Б и Г.",
      "Только В.",
      "А и В.",
      "Б и В."
    ],
    "correct_answer": "А и В."
  },
  {
    "question": "Как Вам следует поступить в данной ситуации?",
    "image": "question_005.jpg",
    "answers": [
      "Уступить дорогу встречному автомобилю.",
      "Действовать по взаимной договоренности с водителем встречного автомобиля.",
      "Проехать первым."
    ],
    "correct_answer": "Проехать первым."
  },
  {
    "question": "В данной ситуации преимущество имеет:",
    "image": "question_006.jpg",
    "answers": [
      "Грузовой автомобиль, так как препятствие находится на полосе движения легкового автомобиля.",
      "Легковой автомобиль, так как он движется на подъем.",
      "Грузовой автомобиль, так как он движется на спуск."
    ],
    "correct_answer": "Легковой автомобиль, так как он движется на подъем."
  },
  {
    "question": "В данной ситуации Вы:",
    "image": "question_007.jpg",
    "answers": [
      "Имеете право проехать первым, так как препятствие находится на полосе движения встречного автомобиля.",
      "Имеете право проехать первым, так как Вы движетесь на спуск.",
      "Должны уступить дорогу, так как встречный автомобиль движется на подъем."
    ],
    "correct_answer": "Должны уступить дорогу, так как встречный автомобиль движется на подъем."
  }
]